mutablezip/__init__.py
mutablezip-2021.dist-info/LICENSE.md
mutablezip-2021.dist-info/WHEEL
mutablezip-2021.dist-info/METADATA
mutablezip-2021.dist-info/RECORD
