Metadata-Version: 2.1
Name: mutablezip
Version: 2021
Summary: Overwrite and remove elements from a zip
Home-page: https://github.com/FHPythonUtils/MutableZip
License: MIT
Author: FredHappyface
Requires-Python: >=3.7,<4.0
Classifier: Development Status :: 5 - Production/Stable
Classifier: Intended Audience :: Developers
Classifier: Intended Audience :: Education
Classifier: License :: OSI Approved :: MIT License
Classifier: Natural Language :: English
Classifier: Operating System :: OS Independent
Classifier: Programming Language :: Python :: 3
Classifier: Programming Language :: Python :: 3.10
Classifier: Programming Language :: Python :: 3.7
Classifier: Programming Language :: Python :: 3.8
Classifier: Programming Language :: Python :: 3.9
Classifier: Programming Language :: Python :: Implementation :: CPython
Classifier: Topic :: Software Development :: Libraries :: Python Modules
Classifier: Topic :: Utilities
Project-URL: Documentation, https://github.com/FHPythonUtils/MutableZip/blob/master/README.md
Project-URL: Repository, https://github.com/FHPythonUtils/MutableZip
